{
  "lookup": {
    "rules": {
      "[{\"prev_action\": {\"action_name\": \"action_listen\"}, \"user\": {\"intent\": \"basic_description\"}}]": "utter_basic_description",
      "[{\"prev_action\": {\"action_name\": \"action_listen\"}, \"user\": {\"intent\": \"basic_description\"}}, {\"prev_action\": {\"action_name\": \"utter_basic_description\"}, \"user\": {\"intent\": \"basic_description\"}}]": "action_listen",
      "[{\"prev_action\": {\"action_name\": \"action_listen\"}, \"user\": {\"intent\": \"nlu_fallback\"}}]": "utter_please_rephrase",
      "[{\"prev_action\": {\"action_name\": \"action_listen\"}, \"user\": {\"intent\": \"nlu_fallback\"}}, {\"prev_action\": {\"action_name\": \"utter_please_rephrase\"}, \"user\": {\"intent\": \"nlu_fallback\"}}]": "action_listen",
      "[{\"active_loop\": {\"name\": \"should_not_be_set\"}, \"prev_action\": {\"action_name\": \"newsletter_form\"}}]": "utter_subscribed",
      "[{\"active_loop\": {\"name\": \"should_not_be_set\"}, \"prev_action\": {\"action_name\": \"newsletter_form\"}}, {\"active_loop\": {\"name\": \"should_not_be_set\"}, \"prev_action\": {\"action_name\": \"utter_subscribed\"}}]": "action_listen",
      "[{\"active_loop\": {\"name\": \"newsletter_form\"}, \"prev_action\": {\"action_name\": \"action_listen\"}, \"user\": {\"intent\": \"greet\"}}]": "utter_ask_email",
      "[{\"active_loop\": {\"name\": \"newsletter_form\"}, \"prev_action\": {\"action_name\": \"action_listen\"}, \"user\": {\"intent\": \"greet\"}}, {\"active_loop\": {\"name\": \"newsletter_form\"}, \"prev_action\": {\"action_name\": \"utter_ask_email\"}, \"user\": {\"intent\": \"greet\"}}]": "action_listen",
      "[{\"prev_action\": {\"action_name\": \"action_listen\"}, \"user\": {\"intent\": \"conformance_check\"}}]": "utter_conformance_check",
      "[{\"prev_action\": {\"action_name\": \"action_listen\"}, \"user\": {\"intent\": \"conformance_check\"}}, {\"prev_action\": {\"action_name\": \"utter_conformance_check\"}, \"user\": {\"intent\": \"conformance_check\"}}]": "action_listen",
      "[{\"prev_action\": {\"action_name\": \"action_listen\"}, \"user\": {\"intent\": \"bot_challenge\"}}]": "utter_iamabot",
      "[{\"prev_action\": {\"action_name\": \"action_listen\"}, \"user\": {\"intent\": \"bot_challenge\"}}, {\"prev_action\": {\"action_name\": \"utter_iamabot\"}, \"user\": {\"intent\": \"bot_challenge\"}}]": "action_listen",
      "[{\"prev_action\": {\"action_name\": \"action_listen\"}, \"user\": {\"intent\": \"compliance\"}}]": "utter_compliance",
      "[{\"prev_action\": {\"action_name\": \"action_listen\"}, \"user\": {\"intent\": \"compliance\"}}, {\"prev_action\": {\"action_name\": \"utter_compliance\"}, \"user\": {\"intent\": \"compliance\"}}]": "action_listen",
      "[{\"prev_action\": {\"action_name\": \"action_listen\"}, \"user\": {\"intent\": \"behavior_check\"}}]": "utter_behavior_check",
      "[{\"prev_action\": {\"action_name\": \"action_listen\"}, \"user\": {\"intent\": \"behavior_check\"}}, {\"prev_action\": {\"action_name\": \"utter_behavior_check\"}, \"user\": {\"intent\": \"behavior_check\"}}]": "action_behavior_check",
      "[{\"prev_action\": {\"action_name\": \"action_listen\"}, \"user\": {\"intent\": \"behavior_check\"}}, {\"prev_action\": {\"action_name\": \"utter_behavior_check\"}, \"user\": {\"intent\": \"behavior_check\"}}, {\"prev_action\": {\"action_name\": \"action_behavior_check\"}, \"user\": {\"intent\": \"behavior_check\"}}]": "action_listen",
      "[{\"prev_action\": {\"action_name\": \"action_listen\"}, \"user\": {\"intent\": \"behavior_search\"}}]": "utter_behavior_search",
      "[{\"prev_action\": {\"action_name\": \"action_listen\"}, \"user\": {\"intent\": \"behavior_search\"}}, {\"prev_action\": {\"action_name\": \"utter_behavior_search\"}, \"user\": {\"intent\": \"behavior_search\"}}]": "action_listen",
      "[{\"prev_action\": {\"action_name\": \"action_listen\"}, \"user\": {\"intent\": \"temporal_contextualization\"}}]": "utter_temporal_contextualization",
      "[{\"prev_action\": {\"action_name\": \"action_listen\"}, \"user\": {\"intent\": \"temporal_contextualization\"}}, {\"prev_action\": {\"action_name\": \"utter_temporal_contextualization\"}, \"user\": {\"intent\": \"temporal_contextualization\"}}]": "action_listen",
      "[{\"prev_action\": {\"action_name\": \"action_listen\"}, \"user\": {\"intent\": \"type_ii\"}}]": "utter_type_ii",
      "[{\"prev_action\": {\"action_name\": \"action_listen\"}, \"user\": {\"intent\": \"type_ii\"}}, {\"prev_action\": {\"action_name\": \"utter_type_ii\"}, \"user\": {\"intent\": \"type_ii\"}}]": "action_type_ii",
      "[{\"prev_action\": {\"action_name\": \"action_listen\"}, \"user\": {\"intent\": \"type_ii\"}}, {\"prev_action\": {\"action_name\": \"utter_type_ii\"}, \"user\": {\"intent\": \"type_ii\"}}, {\"prev_action\": {\"action_name\": \"action_type_ii\"}, \"user\": {\"intent\": \"type_ii\"}}]": "action_listen",
      "[{\"prev_action\": {\"action_name\": \"action_listen\"}, \"user\": {\"intent\": \"query_check\"}}]": "utter_query_check",
      "[{\"prev_action\": {\"action_name\": \"action_listen\"}, \"user\": {\"intent\": \"query_check\"}}, {\"prev_action\": {\"action_name\": \"utter_query_check\"}, \"user\": {\"intent\": \"query_check\"}}]": "action_listen",
      "[{\"prev_action\": {\"action_name\": \"action_listen\"}, \"user\": {\"intent\": \"generate_conformant\"}}]": "utter_generate_conformant",
      "[{\"prev_action\": {\"action_name\": \"action_listen\"}, \"user\": {\"intent\": \"generate_conformant\"}}, {\"prev_action\": {\"action_name\": \"utter_generate_conformant\"}, \"user\": {\"intent\": \"generate_conformant\"}}]": "action_listen",
      "[{\"prev_action\": {\"action_name\": \"action_listen\"}, \"user\": {\"intent\": \"subscribe\"}}]": "newsletter_form",
      "[{\"prev_action\": {\"action_name\": \"action_listen\"}, \"user\": {\"intent\": \"subscribe\"}}, {\"active_loop\": {\"name\": \"newsletter_form\"}, \"prev_action\": {\"action_name\": \"newsletter_form\"}, \"user\": {\"intent\": \"subscribe\"}}]": "action_listen",
      "[{\"prev_action\": {\"action_name\": \"action_listen\"}, \"user\": {\"intent\": \"goodbye\"}}]": "utter_goodbye",
      "[{\"prev_action\": {\"action_name\": \"action_listen\"}, \"user\": {\"intent\": \"goodbye\"}}, {\"prev_action\": {\"action_name\": \"utter_goodbye\"}, \"user\": {\"intent\": \"goodbye\"}}]": "action_listen"
    },
    "rule_only_slots": [],
    "rule_only_loops": [],
    "rules_for_loop_unhappy_path": {
      "[{\"prev_action\": {\"action_name\": \"action_listen\"}}, {\"active_loop\": {\"name\": \"newsletter_form\"}, \"prev_action\": {\"action_name\": \"utter_ask_email\"}, \"user\": {\"intent\": \"greet\"}}]": "do_not_predict_loop_action",
      "[{\"prev_action\": {\"action_name\": \"action_listen\"}}, {\"active_loop\": {\"name\": \"newsletter_form\"}, \"prev_action\": {\"action_name\": \"newsletter_form\"}, \"user\": {\"intent\": \"subscribe\"}}]": "do_not_predict_loop_action"
    },
    "rules_not_in_stories": [
      "[{\"prev_action\": {\"action_name\": \"action_listen\"}, \"user\": {\"intent\": \"query_check\"}}]",
      "[{\"prev_action\": {\"action_name\": \"action_listen\"}, \"user\": {\"intent\": \"goodbye\"}}]",
      "[{\"prev_action\": {\"action_name\": \"action_listen\"}, \"user\": {\"intent\": \"conformance_check\"}}]",
      "predicting default action with intent back",
      "[{\"prev_action\": {\"action_name\": \"action_listen\"}, \"user\": {\"intent\": \"type_ii\"}}]",
      "[{\"prev_action\": {\"action_name\": \"action_listen\"}, \"user\": {\"intent\": \"compliance\"}}, {\"prev_action\": {\"action_name\": \"utter_compliance\"}, \"user\": {\"intent\": \"compliance\"}}]",
      "[{\"prev_action\": {\"action_name\": \"action_listen\"}, \"user\": {\"intent\": \"conformance_check\"}}, {\"prev_action\": {\"action_name\": \"utter_conformance_check\"}, \"user\": {\"intent\": \"conformance_check\"}}]",
      "predicting default action with intent session_start",
      "[{\"prev_action\": {\"action_name\": \"action_listen\"}, \"user\": {\"intent\": \"nlu_fallback\"}}]",
      "[{\"prev_action\": {\"action_name\": \"action_listen\"}, \"user\": {\"intent\": \"behavior_check\"}}]",
      "[{\"prev_action\": {\"action_name\": \"action_listen\"}, \"user\": {\"intent\": \"query_check\"}}, {\"prev_action\": {\"action_name\": \"utter_query_check\"}, \"user\": {\"intent\": \"query_check\"}}]",
      "[{\"prev_action\": {\"action_name\": \"action_listen\"}, \"user\": {\"intent\": \"bot_challenge\"}}]",
      "[{\"active_loop\": {\"name\": \"newsletter_form\"}, \"prev_action\": {\"action_name\": \"action_listen\"}, \"user\": {\"intent\": \"greet\"}}, {\"active_loop\": {\"name\": \"newsletter_form\"}, \"prev_action\": {\"action_name\": \"utter_ask_email\"}, \"user\": {\"intent\": \"greet\"}}]",
      "[{\"prev_action\": {\"action_name\": \"action_listen\"}, \"user\": {\"intent\": \"type_ii\"}}, {\"prev_action\": {\"action_name\": \"utter_type_ii\"}, \"user\": {\"intent\": \"type_ii\"}}, {\"prev_action\": {\"action_name\": \"action_type_ii\"}, \"user\": {\"intent\": \"type_ii\"}}]",
      "[{\"prev_action\": {\"action_name\": \"action_listen\"}, \"user\": {\"intent\": \"behavior_search\"}}]",
      "[{\"prev_action\": {\"action_name\": \"action_listen\"}, \"user\": {\"intent\": \"behavior_search\"}}, {\"prev_action\": {\"action_name\": \"utter_behavior_search\"}, \"user\": {\"intent\": \"behavior_search\"}}]",
      "[{\"prev_action\": {\"action_name\": \"action_listen\"}, \"user\": {\"intent\": \"bot_challenge\"}}, {\"prev_action\": {\"action_name\": \"utter_iamabot\"}, \"user\": {\"intent\": \"bot_challenge\"}}]",
      "predicting default action with intent restart",
      "[{\"prev_action\": {\"action_name\": \"action_listen\"}, \"user\": {\"intent\": \"temporal_contextualization\"}}, {\"prev_action\": {\"action_name\": \"utter_temporal_contextualization\"}, \"user\": {\"intent\": \"temporal_contextualization\"}}]",
      "[{\"prev_action\": {\"action_name\": \"action_listen\"}, \"user\": {\"intent\": \"temporal_contextualization\"}}]",
      "[{\"prev_action\": {\"action_name\": \"action_listen\"}, \"user\": {\"intent\": \"generate_conformant\"}}, {\"prev_action\": {\"action_name\": \"utter_generate_conformant\"}, \"user\": {\"intent\": \"generate_conformant\"}}]",
      "[{\"prev_action\": {\"action_name\": \"action_listen\"}, \"user\": {\"intent\": \"goodbye\"}}, {\"prev_action\": {\"action_name\": \"utter_goodbye\"}, \"user\": {\"intent\": \"goodbye\"}}]",
      "[{\"prev_action\": {\"action_name\": \"action_listen\"}, \"user\": {\"intent\": \"basic_description\"}}]",
      "[{\"active_loop\": {\"name\": \"newsletter_form\"}, \"prev_action\": {\"action_name\": \"action_listen\"}, \"user\": {\"intent\": \"greet\"}}]",
      "[{\"prev_action\": {\"action_name\": \"action_listen\"}, \"user\": {\"intent\": \"nlu_fallback\"}}, {\"prev_action\": {\"action_name\": \"utter_please_rephrase\"}, \"user\": {\"intent\": \"nlu_fallback\"}}]",
      "[{\"prev_action\": {\"action_name\": \"action_listen\"}, \"user\": {\"intent\": \"type_ii\"}}, {\"prev_action\": {\"action_name\": \"utter_type_ii\"}, \"user\": {\"intent\": \"type_ii\"}}]",
      "[{\"prev_action\": {\"action_name\": \"action_listen\"}, \"user\": {\"intent\": \"basic_description\"}}, {\"prev_action\": {\"action_name\": \"utter_basic_description\"}, \"user\": {\"intent\": \"basic_description\"}}]",
      "[{\"active_loop\": {\"name\": \"should_not_be_set\"}, \"prev_action\": {\"action_name\": \"newsletter_form\"}}]",
      "[{\"prev_action\": {\"action_name\": \"action_listen\"}, \"user\": {\"intent\": \"generate_conformant\"}}]",
      "handling active loops and forms - newsletter_form",
      "[{\"prev_action\": {\"action_name\": \"action_listen\"}, \"user\": {\"intent\": \"behavior_check\"}}, {\"prev_action\": {\"action_name\": \"utter_behavior_check\"}, \"user\": {\"intent\": \"behavior_check\"}}]",
      "[{\"active_loop\": {\"name\": \"should_not_be_set\"}, \"prev_action\": {\"action_name\": \"newsletter_form\"}}, {\"active_loop\": {\"name\": \"should_not_be_set\"}, \"prev_action\": {\"action_name\": \"utter_subscribed\"}}]",
      "[{\"prev_action\": {\"action_name\": \"action_listen\"}, \"user\": {\"intent\": \"behavior_check\"}}, {\"prev_action\": {\"action_name\": \"utter_behavior_check\"}, \"user\": {\"intent\": \"behavior_check\"}}, {\"prev_action\": {\"action_name\": \"action_behavior_check\"}, \"user\": {\"intent\": \"behavior_check\"}}]",
      "[{\"prev_action\": {\"action_name\": \"action_listen\"}, \"user\": {\"intent\": \"compliance\"}}]"
    ]
  }
}